LWD_utils/__init__.py
LWD_utils/application.py
LWD_utils/common_util.py
LWD_utils/constant.py
LWD_utils/crawler_util.py
LWD_utils/document_util.py
LWD_utils/global_val.py
LWD_utils/office_util.py
LWD_utils/pdf_util.py
LWD_utils/research_util.py
LWD_utils/translate_util.py
LWD_utils/proxypool/__init__.py
LWD_utils/proxypool/scheduler.py
LWD_utils/proxypool/setting.py
LWD_utils/proxypool/crawlers/__init__.py
LWD_utils/proxypool/crawlers/base.py
LWD_utils/proxypool/crawlers/private/__init__.py
LWD_utils/proxypool/crawlers/public/__init__.py
LWD_utils/proxypool/crawlers/public/daili66.py
LWD_utils/proxypool/crawlers/public/data5u.py
LWD_utils/proxypool/crawlers/public/fatezero.py
LWD_utils/proxypool/crawlers/public/goubanjia.py
LWD_utils/proxypool/crawlers/public/ihuan.py
LWD_utils/proxypool/crawlers/public/ip3366.py
LWD_utils/proxypool/crawlers/public/ip89.py
LWD_utils/proxypool/crawlers/public/iphai.py
LWD_utils/proxypool/crawlers/public/jiangxianli.py
LWD_utils/proxypool/crawlers/public/kuaidaili.py
LWD_utils/proxypool/crawlers/public/seofangfa.py
LWD_utils/proxypool/crawlers/public/taiyangdaili.py
LWD_utils/proxypool/crawlers/public/xiaoshudaili.py
LWD_utils/proxypool/crawlers/public/xicidaili.py
LWD_utils/proxypool/crawlers/public/xiladaili.py
LWD_utils/proxypool/crawlers/public/yqie.py
LWD_utils/proxypool/crawlers/public/zhandaye.py
LWD_utils/proxypool/exceptions/__init__.py
LWD_utils/proxypool/exceptions/empty.py
LWD_utils/proxypool/processors/__init__.py
LWD_utils/proxypool/processors/getter.py
LWD_utils/proxypool/processors/server.py
LWD_utils/proxypool/processors/tester.py
LWD_utils/proxypool/schemas/__init__.py
LWD_utils/proxypool/schemas/proxy.py
LWD_utils/proxypool/storages/__init__.py
LWD_utils/proxypool/storages/proxy_dict.py
LWD_utils/proxypool/storages/redis.py
LWD_utils/proxypool/utils/__init__.py
LWD_utils/proxypool/utils/proxy.py
LWD_utils-1.0.0.dist-info/LICENSE
LWD_utils-1.0.0.dist-info/METADATA
LWD_utils-1.0.0.dist-info/WHEEL
LWD_utils-1.0.0.dist-info/top_level.txt
LWD_utils-1.0.0.dist-info/RECORD
